{
  "pools": [
    {
      "name": "goblin_drops",
      "entries": [
        {
          "entryName": "minecraft:iron_ingot",
          "weight": 1,
          "quality": 0,
          "type": "item",
          "functions": [
            {
              "count": {
                "min": 1.0,
                "max": 2.0
              },
              "function": "minecraft:set_count"
            },
            {
              "count": {
                "min": 0.0,
                "max": 1.0
              },
              "function": "minecraft:looting_enchant"
            }
          ],
          "name": "minecraft:iron_ingot"
        }
      ],
      "rolls": 1.0
    },
    {
      "name": "goblin_rare_drops",
      "entries": [
        {
          "entryName": "minecraft:emerald",
          "weight": 1,
          "quality": 0,
          "type": "item",
          "functions": [
            {
              "count": {
                "min": -4.0,
                "max": 1.0
              },
              "function": "minecraft:set_count"
            },
            {
              "count": {
                "min": -2.0,
                "max": 1.0
              },
              "function": "minecraft:looting_enchant"
            }
          ],
          "name": "minecraft:emerald"
        }
      ],
      "rolls": 1.0,
      "conditions": [
        {
          "inverse": false,
          "condition": "minecraft:killed_by_player"
        }
      ]
    }
  ]
}