{
    "name" : "_futurepack_lvl_all_loot",
    "loot_rules" : [
		{	
			"type" : "FOOD", 
			"loot" : [
				{"data" : {"name" : "fp:erse"}, "min" : 1, "max" : 3}
			],
			"level" : 0,
			"each" : true,
			"quantity" : 3
		},
		{	
			"type" : "ORE", 
			"loot" : [
				{"data" : {"name" : "primal:tin_ingot", "min" : 1, "max" : 3}, "weight" : 10},
				{"data" : {"name" : "immersiveengineering:metal", "meta" : 0, "min" : 1, "max" : 3}, "weight" : 9},
				{"data" : {"name" : "immersiveengineering:metal", "meta" : 1, "min" : 1, "max" : 3}, "weight" : 3},
				{"data" : {"name" : "immersiveengineering:metal", "meta" : 2, "min" : 1, "max" : 3}, "weight" : 6},
				{"data" : {"name" : "immersiveengineering:metal", "meta" : 3, "min" : 1, "max" : 3}, "weight" : 3},
				{"data" : {"name" : "immersiveengineering:metal", "meta" : 4, "min" : 1, "max" : 3}, "weight" : 4},
				{"data" : {"name" : "immersiveengineering:metal", "meta" : 5, "min" : 1, "max" : 3}, "weight" : 1},
				{"data" : {"name" : "immersiveengineering:metal", "meta" : 6, "min" : 1, "max" : 3}, "weight" : 1},
				{"data" : {"name" : "immersiveengineering:metal", "meta" : 7, "min" : 1, "max" : 3}, "weight" : 1},
				{"data" : {"name" : "immersiveengineering:metal", "meta" : 8, "min" : 1, "max" : 3}, "weight" : 1}
			],
			"level" : 0,
			"each" : true,
			"quantity" : 6
		}
    ]
}

