{
    "name":"botania",
    "namespace":"botania",
    "criteria":{
        "biomeTypes":[
            "PLAINS",
            "FOREST",
            "MAGICAL",
            "LUSH",
            "JUNGLE",
            "WET",
            "SAVANNA",
            "DENSE"
        ],
        "dimensionWL":[
            0
        ],
        "weight":1
    },
    "exclusive":true,
	"inherit":[
		"default:_loot_all",
        "default:_loot0",
        "default:_loot1",
        "default:_loot2",
        "default:_loot3",
        "default:_loot4",
        "default:_rooms",
        "default:base"
	],
    "tower":{
        "type":"JUNGLE",
        "theme":{
            "base":"ETHO",
            "primary":{
                "walls":{
                    "type":"METABLOCK",
                    "data":{
                        "name":"biomesoplenty:planks_0",
                        "meta":9
                    }
                },
                "pillar":{
                    "type":"METABLOCK",
                    "data":{
						"name":"biomesoplenty:log_2",
                        "meta":5
					}
                },
                "stair":{
                    "type":"METABLOCK",
                    "data":{
                        "name":"biomesoplenty:willow_stairs"
                    }
                },
                "floor":{
                    "name":"quark:stained_clay_tiles",
                    "meta":5
                }
            },
            "secondary":{
                "walls":{
                    "type":"METABLOCK",
                    "data":{
                        "name":"biomesoplenty:planks_0",
                        "meta":8
                    }
                },
                "pillar":{
                    "type":"METABLOCK",
                    "data":{
                        "name":"biomesoplenty:log_2",
                        "meta":4
                    }
                },
                "stair":{
                    "type":"METABLOCK",
                    "data":{
                        "name":"quark:stained_clay_tiles_red_stairs"
                    }
                },
                "floor":{
                    "type":"METABLOCK",
                    "data":{
                        "name":"quark:stained_clay_tiles",
                        "meta":14
                    }
                }
            }
        }
    },
    "levels":{
        "0":{
            "theme":{
                "base":"QUARTZ",
                "primary":{
                    "walls":{
                        "type":"METABLOCK",
                        "data":{
                            "name":"botania:livingwood",
                            "meta":2
                        }
                    },
                    "pillar":{
                        "type":"METABLOCK",
                        "data":{
                            "name":"minecraft:log",
                            "meta":1
                        }
                    },
                    "stair":{
                        "type":"METABLOCK",
                        "data":{
                            "name":"quark:stained_clay_tiles_brown_stairs"
                        }
                    },
                    "floor":{
                        "type":"METABLOCK",
                        "data":{
                            "name":"botanicaladdons:irisDirt",
                            "meta":12
                        }
                    }
                },
                "secondary":{
                    "walls":{
                        "type":"METABLOCK",
                        "data":{
                            "name":"chisel:limestone1",
                            "meta":2
                        }
                    },
                    "pillar":{
                        "type":"METABLOCK",
                        "data":{
                            "name":"chisel:limestoneextra",
                            "meta":4
                        }
                    },
                    "stair":{
                        "type":"METABLOCK",
                        "data":{
                            "name":"natura:overworld_stairs_silverbell"
                        }
                    },
                    "floor":{
                        "type":"METABLOCK",
                        "data":{
                            "name":"chisel:limestone",
                            "meta":5
                        }
                    }
                }
            }
        },
        "1":{
            "theme":{
                "base":"QUARTZ",
                "primary":{
                    "walls":{
                        "type":"JUMBLE",
                        "data":[
							{
								"name":"rockhounding_rocks:bricksA",
								"meta":11
							},
							{
								"name":"rockhounding_rocks:shortsA",
								"meta":11
							}
						]
                    },
                    "pillar":{
                        "type":"METABLOCK",
                        "data":{
                            "name":"botanicaladdons:irisLog0",
                            "meta":3
                        }
                    },
                    "stair":{
                        "type":"METABLOCK",
                        "data":{
                            "name":"biomesoplenty:magic_stairs"
                        }
                    },
                    "floor":{
                        "type":"METABLOCK",
                        "data":{
                            "name":"botanicaladdons:irisDirt",
                            "meta":3
                        }
                    }
                },
                "secondary":{
                    "walls":{
                        "type":"LAYERS",
                        "data":[
                            {
                                "name":"botania:quartzTypeMana",
                                "meta":1
                            },
                            {
                                "name":"chisel:diorite1",
                                "meta":6
                            }
                        ]
                    },
                    "pillar":{
                        "type":"METABLOCK",
                        "data":{
                            "name":"botania:quartzTypeMana",
                            "meta":2
                        }
                    },
                    "stair":{
                        "type":"METABLOCK",
                        "data":{
                            "name":"botania:quartzStairsMana"
                        }
                    },
                    "floor":{
                        "type":"METABLOCK",
                        "data":{
                            "name":"chisel:diorite1",
							"meta":1
                        }
                    }
                }
            }
        },
        "2":{
            "theme":{
                "base":"ENIKO",
                "primary":{
                    "walls":{
                        "name":"quark:midori_block"
                    },
                    "pillar":{
                        "name":"forestry:logs.4",
						"meta":1
                    },
                    "stair":{
                        "name":"quark:midori_block_stairs"
                    },
                    "floor":{
						"name":"botanicaladdons:irisDirt",
						"meta":13
                    }
                },
                "secondary":{
                    "walls":{
                        "type":"METABLOCK",
                        "data":{
                            "name":"botania:quartzTypeElf",
                            "meta":1
                        }
                    },
                    "pillar":{
                        "type":"METABLOCK",
                        "data":{
                            "name":"botania:quartzTypeElf",
                            "meta":2
                        }
                    },
                    "stair":{
                        "name":"botania:quartzStairsElf"
                    },
                    "floor":{
                        "type":"METABLOCK",
                        "data":{
                            "name":"botania:quartzTypeElf",
                            "meta":4
                        }
                    }
                }
            }
        },
		"3":{
            "theme":{
                "base":"ENIKO",
                "primary":{
                    "walls":{
                        "type":"JUMBLE",
						"data":[
							{
								"name":"chisel:valentines",
								"meta":4
							},
							{
								"name":"chisel:valentines",
								"meta":5
							},
							{
								"name":"chisel:valentines",
								"meta":6
							},
							{
								"name":"chisel:valentines",
								"meta":8
							}
						]
                    },
                    "pillar":{
                        "name":"botanicaladdons:irisLog1",
						"meta":2
                    },
                    "stair":{
                        "name":"natura:overworld_stairs_eucalyptus"
                    },
                    "floor":{
						"name":"botanicaladdons:irisDirt",
						"meta":6
                    }
                },
                "secondary":{
                    "walls":{
                        "type":"METABLOCK",
                        "data":{
                            "name":"botania:quartzTypeLavender",
                            "meta":1
                        }
                    },
                    "pillar":{
                        "type":"METABLOCK",
                        "data":{
                            "name":"botania:quartzTypeLavender",
                            "meta":2
                        }
                    },
                    "stair":{
                        "name":"botania:quartzStairsLavender"
                    },
                    "floor":{
                        "type":"METABLOCK",
                        "data":{
                            "name":"botania:quartzTypeLavender",
                            "meta":4
                        }
                    }
                }
            }
        },
		"4":{
			"theme":{
				"base":"RAINBOW",
                "primary":{
                    "walls":{
                        "type":"JUMBLE",
                        "data":[
                            {
                                "name":"rockhounding_rocks:bricksVanilla",
                                "meta":14
                            },
                            {
                                "name":"rockhounding_rocks:shortsVanilla",
                                "meta":14
                            }
                        ]    
                    },
                    "pillar":{
                        "name":"forestry:logs.fireproof.6",
                        "meta":1
                    },
                    "stair":{
                        "name":"forestry:stairs.fireproof.cocobolo"
                    },
                    "floor":{
                        "type":"WEIGHTED",
                        "data":[
                            {
                                "name":"botania:altGrass",
                                "meta":3,
                                "weight":500
                            },
                            {
                                "name":"magma",
                                "weight":50
                            },
                            {
                                "name":"botania:enchantedSoil",
                                "weight":1
                            }
                        ]
                    }
                },
                "secondary":{
                    "walls":{
                        "type":"JUMBLE",
                        "data":[
                            {
                                "name":"botania:biomeStoneB",
                                "meta":7
                            },
                            {
                                "name":"botania:biomeStoneA",
                                "meta":7
                            },
                            {
                                "name":"botania:biomeStoneA",
                                "meta":15
                            }
                            
                        ]
                    },
                    "pillar":{
                        "name":"chisel:netherbrick",
                        "meta":7
                    },
                    "stair":{
                        "name":"tconstruct:lavawood_stairs"
                    }
                }
			}
		}
    }
}